numsci-1.0.0.dist-info/METADATA
numsci-1.0.0.dist-info/WHEEL
numsci-1.0.0.dist-info/LICENSE
numsci/optimize/libminpack.so
numsci/__init__.py
numsci/optimize/__init__.py
numsci/optimize/minpackcore.py
numsci-1.0.0.dist-info/RECORD
