Metadata-Version: 2.1
Name: numsci
Version: 1.0.0
Summary: A Numba-compatible Scipy port
License: BSD 3-Clause License
Requires-Dist: numpy
Requires-Dist: numba
